{
  "text": {
    "안녕": 18,
    "안녕하세요": 19,
    "하이": 32,
    "좋은": 30,
    "아침": 17,
    "안녕히": 20,
    "계세요": 4,
    "잘": 27,
    "가요": 0,
    "바이": 15,
    "점심": 29,
    "뭐": 13,
    "먹지": 11,
    "오늘": 22,
    "저녁": 28,
    "뭐야": 14,
    "메뉴": 12,
    "추천해줘": 31,
    "먹을까": 10,
    "감자": 2,
    "요리": 23,
    "있어": 25,
    "계란으로": 3,
    "만들": 9,
    "수": 16,
    "있는": 24,
    "알려줘": 21,
    "간단한": 1,
    "두부": 7,
    "닭고기": 6,
    "들어간": 8,
    "김치": 5,
    "있을까": 26
  },
  "intent": {
    "greet": 1,
    "goodbye": 0,
    "recommend_menu": 2
  },
  "response": null,
  "action_name": {
    "action_listen": 6,
    "action_restart": 8,
    "action_session_start": 10,
    "action_default_fallback": 4,
    "action_deactivate_loop": 1,
    "action_revert_fallback_events": 9,
    "action_default_ask_affirmation": 2,
    "action_default_ask_rephrase": 3,
    "action_two_stage_fallback": 11,
    "action_unlikely_intent": 12,
    "action_back": 0,
    "action_extract_slots": 5,
    "action_recommend_menu": 7,
    "utter_goodbye": 13,
    "utter_greet": 14
  },
  "action_text": null,
  "intent_response_key": null
}